{
    "trucks": [
        {
            "available": true,
            "brand": "TOTAL",
            "category": "TRUCK",
            "fuel": 67.0,
            "inspectionCost": -1,
            "inspectionDate": "no date",
            "inspectionID": -1,
            "inspectionToday": "no date",
            "insuranceEndDate": "no date",
            "insuranceID": -1,
            "insuranceMonthlyCost": -1,
            "insuranceStartDate": "no date",
            "insuranceToday": "no date",
            "licensePlate": "00-00-03",
            "mileage": 76456.0,
            "model": "20",
            "vslID": -1,
            "weightCapacity": 3527.0,
            "year": 2009
        },
        {
            "available": false,
            "brand": "Tesla",
            "category": "TRUCK",
            "fuel": 54.0,
            "inspectionCost": -1,
            "inspectionDate": "no date",
            "inspectionID": -1,
            "inspectionToday": "no date",
            "insuranceEndDate": "no date",
            "insuranceID": -1,
            "insuranceMonthlyCost": -1,
            "insuranceStartDate": "no date",
            "insuranceToday": "no date",
            "licensePlate": "LU-65-CA",
            "mileage": 67954.0,
            "model": "Model 3",
            "vslID": -1,
            "weightCapacity": 3210.0,
            "year": 2018
        },
        {
            "available": true,
            "brand": "ROBUST",
            "category": "TRUCK",
            "fuel": 79.0,
            "inspectionCost": -1,
            "inspectionDate": "no date",
            "inspectionID": -1,
            "inspectionToday": "no date",
            "insuranceEndDate": "no date",
            "insuranceID": -1,
            "insuranceMonthlyCost": -1,
            "insuranceStartDate": "no date",
            "insuranceToday": "no date",
            "licensePlate": "00-00-05",
            "mileage": 23456.0,
            "model": "TITAN",
            "vslID": -1,
            "weightCapacity": 654.0,
            "year": 2015
        }
    ],
    "vans": [
        {
            "available": true,
            "brand": "GUNA",
            "category": "VAN",
            "fuel": 23.0,
            "inspectionCost": -1,
            "inspectionDate": "no date",
            "inspectionID": -1,
            "inspectionToday": "no date",
            "insuranceEndDate": "no date",
            "insuranceID": -1,
            "insuranceMonthlyCost": -1,
            "insuranceStartDate": "no date",
            "insuranceToday": "no date",
            "licensePlate": "00-00-02",
            "mileage": 543667.0,
            "model": "MASTER",
            "spaceCapacity": 20.0,
            "vslID": -1,
            "year": 2025
        },
        {
            "available": true,
            "brand": "BMW",
            "category": "VAN",
            "fuel": 80.0,
            "inspectionCost": 30.0,
            "inspectionDate": "10/6/2025",
            "inspectionID": 2,
            "inspectionToday": "13/6/2025",
            "insuranceEndDate": "11/6/2026",
            "insuranceID": 2,
            "insuranceMonthlyCost": 30.0,
            "insuranceStartDate": "11/6/2025",
            "insuranceToday": "13/6/2025",
            "licensePlate": "25-qi-56",
            "mileage": 140000.0,
            "model": "Serie1",
            "spaceCapacity": 100.0,
            "vslID": 1,
            "year": 2015
        },
        {
            "available": true,
            "brand": "SPEEDY",
            "category": "VAN",
            "fuel": 65.0,
            "inspectionCost": -1,
            "inspectionDate": "no date",
            "inspectionID": -1,
            "inspectionToday": "no date",
            "insuranceEndDate": "no date",
            "insuranceID": -1,
            "insuranceMonthlyCost": -1,
            "insuranceStartDate": "no date",
            "insuranceToday": "no date",
            "licensePlate": "00-00-04",
            "mileage": 120000.0,
            "model": "EXPRESS",
            "spaceCapacity": 34.0,
            "vslID": -1,
            "year": 2023
        },
        {
            "available": true,
            "brand": "SERVICE",
            "category": "VAN",
            "fuel": 32.0,
            "inspectionCost": 39.99,
            "inspectionDate": "1/7/2025",
            "inspectionID": 3,
            "inspectionToday": "13/6/2025",
            "insuranceEndDate": "no date",
            "insuranceID": -1,
            "insuranceMonthlyCost": -1,
            "insuranceStartDate": "no date",
            "insuranceToday": "no date",
            "licensePlate": "00-00-06",
            "mileage": 589387.0,
            "model": "COMPLETE",
            "spaceCapacity": 12.9,
            "vslID": -1,
            "year": 2009
        }
    ]
}
